CHANGES.txt
CONTRIBUTORS.txt
MANIFEST.in
README.txt
setup.cfg
setup.py
collective/__init__.py
collective.barcamp.egg-info/PKG-INFO
collective.barcamp.egg-info/SOURCES.txt
collective.barcamp.egg-info/dependency_links.txt
collective.barcamp.egg-info/entry_points.txt
collective.barcamp.egg-info/namespace_packages.txt
collective.barcamp.egg-info/not-zip-safe
collective.barcamp.egg-info/paster_plugins.txt
collective.barcamp.egg-info/requires.txt
collective.barcamp.egg-info/top_level.txt
collective/barcamp/README.txt
collective/barcamp/__init__.py
collective/barcamp/config.py
collective/barcamp/configure.zcml
collective/barcamp/indexer.py
collective/barcamp/indexers.zcml
collective/barcamp/unrestrictor.py
collective/barcamp/browser/__init__.py
collective/barcamp/browser/configure.zcml
collective/barcamp/browser/eventview.py
collective/barcamp/browser/userform.py
collective/barcamp/browser/templates/barcampevent.pt
collective/barcamp/browser/templates/barcampsession.pt
collective/barcamp/content/__init__.py
collective/barcamp/content/barcampevent.py
collective/barcamp/content/barcampparticipant.py
collective/barcamp/content/barcampsession.py
collective/barcamp/content/configure.zcml
collective/barcamp/interfaces/__init__.py
collective/barcamp/interfaces/barcampevent.py
collective/barcamp/interfaces/barcampparticipant.py
collective/barcamp/interfaces/barcampsession.py
collective/barcamp/portlets/__init__.py
collective/barcamp/portlets/configure.zcml
collective/barcamp/profiles/default/factorytool.xml
collective/barcamp/profiles/default/metadata.xml
collective/barcamp/profiles/default/portlets.xml
collective/barcamp/profiles/default/rolemap.xml
collective/barcamp/profiles/default/types.xml
collective/barcamp/profiles/default/types/BarcampEvent.xml
collective/barcamp/profiles/default/types/BarcampParticipant.xml
collective/barcamp/profiles/default/types/BarcampSession.xml
collective/barcamp/tests/__init__.py
collective/barcamp/tests/base.py
collective/barcamp/tests/test_doctest.py
docs/HISTORY.txt
docs/INSTALL.txt
docs/LICENSE.GPL
docs/LICENSE.txt